menglingflow_process/__init__.py
menglingflow_process/__thread_task__.py
menglingflow_process/key_value.py
menglingflow_process/radar.py
menglingflow_process/schedule.py
menglingflow_process/combine_data2/config.py
menglingflow_process/combine_data2/data.py
menglingflow_process/combine_data2/insert.py
menglingflow_process/combine_data2/main.py
menglingflow_process/combine_data2/模板.py
menglingflow_process/week_schedule/main.py
menglingflow_process/week_schedule/schedule.py
menglingflow_process/week_schedule/base/get.py
menglingflow_process/week_schedule/base/set.py
menglingflow_process/week_schedule/base/config/arg.py
menglingflow_process/week_schedule/base/config/out.py
menglingflow_process/week_schedule/base/config/sqlt.py
menglingflow_process/week_schedule/base/config/status.py
menglingflow_process-1.1.8.dist-info/METADATA
menglingflow_process-1.1.8.dist-info/WHEEL
menglingflow_process-1.1.8.dist-info/entry_points.txt
menglingflow_process-1.1.8.dist-info/top_level.txt
menglingflow_process-1.1.8.dist-info/RECORD
