Metadata-Version: 2.1
Name: menglingflow_process
Version: 1.1.8
Summary: 工业化! yyds
Home-page: https://www.python.org
Author: mengling
Author-email: 1321443305@qq.com
Requires-Python: >=3.6
Requires-Dist: click
Requires-Dist: numpy
Requires-Dist: pandas
Requires-Dist: menglingtool
Requires-Dist: menglingtool-redis
Requires-Dist: menglingtool-sqltools
Requires-Dist: menglingtool-handle
Requires-Dist: menglingtool-spiders
